LICENSE
MANIFEST.in
README.md
setup.py
a10_neutronclient/__init__.py
a10_neutronclient/a10_certificate.py
a10_neutronclient/a10_device_instance.py
a10_neutronclient/a10_scaling_group.py
a10_neutronclient/client_extension.py
a10_neutronclient.egg-info/PKG-INFO
a10_neutronclient.egg-info/SOURCES.txt
a10_neutronclient.egg-info/dependency_links.txt
a10_neutronclient.egg-info/entry_points.txt
a10_neutronclient.egg-info/requires.txt
a10_neutronclient.egg-info/top_level.txt